VFDBQuery/__init__.py
VFDBQuery/vfdbQuery.py
vfdbQuery/__init__.py
vfdbQuery/vfdbQuery.py
vfdbQuery-0.0.1.dist-info/LICENSE
vfdbQuery-0.0.1.dist-info/METADATA
vfdbQuery-0.0.1.dist-info/WHEEL
vfdbQuery-0.0.1.dist-info/entry_points.txt
vfdbQuery-0.0.1.dist-info/top_level.txt
vfdbQuery-0.0.1.dist-info/RECORD
