Metadata-Version: 2.1
Name: vfdbQuery
Version: 0.0.1
Summary: Package for quickly querying an assembly against the VFDB
Home-page: https://github.com/bfssi-forest-dussault/vfdbQuery
Author: Forest Dussault
Author-email: forest.dussault@canada.ca
License: UNKNOWN
Platform: UNKNOWN
Requires-Python: ~=3.6
Requires-Dist: click
Requires-Dist: pandas
Requires-Dist: matplotlib
Requires-Dist: numpy
